new_dt_algorithm.py
new_dt_algorithm/__init__.py
new_dt_algorithm/new_dt_algorithm.py
new_dt_algorithm-1.0.dist-info/METADATA
new_dt_algorithm-1.0.dist-info/WHEEL
new_dt_algorithm-1.0.dist-info/top_level.txt
new_dt_algorithm-1.0.dist-info/RECORD
